README
setup.py
forrin/__init__.py
forrin/cs.py
forrin/en.py
forrin/extract.py
forrin/message.py
forrin/template.py
forrin/translator.py
forrin.egg-info/PKG-INFO
forrin.egg-info/SOURCES.txt
forrin.egg-info/dependency_links.txt
forrin.egg-info/entry_points.txt
forrin.egg-info/requires.txt
forrin.egg-info/top_level.txt