Metadata-Version: 1.0
Name: forrin
Version: 0.1-alpha
Summary: Localization helpers
Home-page: UNKNOWN
Author: Petr Viktorin
Author-email: encukou@gmail.com
License: UNKNOWN
Platform: UNKNOWN
